{
  "concept_id": "CESD_ITEM_EVERYTHING_EFFORT",
  "exam": "H",
  "by": {
    "all": [
      {
        "label": "All",
        "n": 3474,
        "missing": 2,
        "n_levels": 5,
        "mode_level": "\"Rarely or none of the time\"",
        "freq": [
          {
            "level": "\"Rarely or none of the time\"",
            "count": 2077,
            "pct": 59.8
          },
          {
            "level": "Some of the time",
            "count": 990,
            "pct": 28.5
          },
          {
            "level": "Much of the time",
            "count": 243,
            "pct": 7
          },
          {
            "level": "Most or all of the time",
            "count": 162,
            "pct": 4.7
          },
          {
            "level": "(Missing)",
            "count": 2,
            "pct": 0.1
          }
        ]
      }
    ],
    "sex": [
      {
        "label": "sex: 1",
        "n": 1507,
        "missing": 0,
        "n_levels": 4,
        "mode_level": "\"Rarely or none of the time\"",
        "freq": [
          {
            "level": "\"Rarely or none of the time\"",
            "count": 893,
            "pct": 59.3
          },
          {
            "level": "Some of the time",
            "count": 448,
            "pct": 29.7
          },
          {
            "level": "Much of the time",
            "count": 100,
            "pct": 6.6
          },
          {
            "level": "Most or all of the time",
            "count": 66,
            "pct": 4.4
          }
        ]
      },
      {
        "label": "sex: 2",
        "n": 1967,
        "missing": 2,
        "n_levels": 5,
        "mode_level": "\"Rarely or none of the time\"",
        "freq": [
          {
            "level": "\"Rarely or none of the time\"",
            "count": 1184,
            "pct": 60.2
          },
          {
            "level": "Some of the time",
            "count": 542,
            "pct": 27.6
          },
          {
            "level": "Much of the time",
            "count": 143,
            "pct": 7.3
          },
          {
            "level": "Most or all of the time",
            "count": 96,
            "pct": 4.9
          },
          {
            "level": "(Missing)",
            "count": 2,
            "pct": 0.1
          }
        ]
      }
    ],
    "race": [
      {
        "label": "race: 4",
        "n": 1624,
        "missing": 1,
        "n_levels": 5,
        "mode_level": "\"Rarely or none of the time\"",
        "freq": [
          {
            "level": "\"Rarely or none of the time\"",
            "count": 880,
            "pct": 54.2
          },
          {
            "level": "Some of the time",
            "count": 463,
            "pct": 28.5
          },
          {
            "level": "Much of the time",
            "count": 158,
            "pct": 9.7
          },
          {
            "level": "Most or all of the time",
            "count": 122,
            "pct": 7.5
          },
          {
            "level": "(Missing)",
            "count": 1,
            "pct": 0.1
          }
        ]
      },
      {
        "label": "race: 5",
        "n": 1850,
        "missing": 1,
        "n_levels": 5,
        "mode_level": "\"Rarely or none of the time\"",
        "freq": [
          {
            "level": "\"Rarely or none of the time\"",
            "count": 1197,
            "pct": 64.7
          },
          {
            "level": "Some of the time",
            "count": 527,
            "pct": 28.5
          },
          {
            "level": "Much of the time",
            "count": 85,
            "pct": 4.6
          },
          {
            "level": "Most or all of the time",
            "count": 40,
            "pct": 2.2
          },
          {
            "level": "(Missing)",
            "count": 1,
            "pct": 0.1
          }
        ]
      }
    ],
    "center": [
      {
        "label": "center: 1",
        "n": 817,
        "missing": 1,
        "n_levels": 5,
        "mode_level": "\"Rarely or none of the time\"",
        "freq": [
          {
            "level": "\"Rarely or none of the time\"",
            "count": 484,
            "pct": 59.2
          },
          {
            "level": "Some of the time",
            "count": 217,
            "pct": 26.6
          },
          {
            "level": "Most or all of the time",
            "count": 60,
            "pct": 7.3
          },
          {
            "level": "Much of the time",
            "count": 55,
            "pct": 6.7
          },
          {
            "level": "(Missing)",
            "count": 1,
            "pct": 0.1
          }
        ]
      },
      {
        "label": "center: 2",
        "n": 787,
        "missing": 0,
        "n_levels": 4,
        "mode_level": "\"Rarely or none of the time\"",
        "freq": [
          {
            "level": "\"Rarely or none of the time\"",
            "count": 464,
            "pct": 59
          },
          {
            "level": "Some of the time",
            "count": 222,
            "pct": 28.2
          },
          {
            "level": "Much of the time",
            "count": 66,
            "pct": 8.4
          },
          {
            "level": "Most or all of the time",
            "count": 35,
            "pct": 4.4
          }
        ]
      },
      {
        "label": "center: 3",
        "n": 915,
        "missing": 1,
        "n_levels": 5,
        "mode_level": "\"Rarely or none of the time\"",
        "freq": [
          {
            "level": "\"Rarely or none of the time\"",
            "count": 559,
            "pct": 61.1
          },
          {
            "level": "Some of the time",
            "count": 270,
            "pct": 29.5
          },
          {
            "level": "Much of the time",
            "count": 55,
            "pct": 6
          },
          {
            "level": "Most or all of the time",
            "count": 30,
            "pct": 3.3
          },
          {
            "level": "(Missing)",
            "count": 1,
            "pct": 0.1
          }
        ]
      },
      {
        "label": "center: 4",
        "n": 955,
        "missing": 0,
        "n_levels": 4,
        "mode_level": "\"Rarely or none of the time\"",
        "freq": [
          {
            "level": "\"Rarely or none of the time\"",
            "count": 570,
            "pct": 59.7
          },
          {
            "level": "Some of the time",
            "count": 281,
            "pct": 29.4
          },
          {
            "level": "Much of the time",
            "count": 67,
            "pct": 7
          },
          {
            "level": "Most or all of the time",
            "count": 37,
            "pct": 3.9
          }
        ]
      }
    ],
    "race_sex": [
      {
        "label": "race: 4 · sex: 1",
        "n": 648,
        "missing": 0,
        "n_levels": 4,
        "mode_level": "\"Rarely or none of the time\"",
        "freq": [
          {
            "level": "\"Rarely or none of the time\"",
            "count": 334,
            "pct": 51.5
          },
          {
            "level": "Some of the time",
            "count": 201,
            "pct": 31
          },
          {
            "level": "Much of the time",
            "count": 62,
            "pct": 9.6
          },
          {
            "level": "Most or all of the time",
            "count": 51,
            "pct": 7.9
          }
        ]
      },
      {
        "label": "race: 4 · sex: 2",
        "n": 976,
        "missing": 1,
        "n_levels": 5,
        "mode_level": "\"Rarely or none of the time\"",
        "freq": [
          {
            "level": "\"Rarely or none of the time\"",
            "count": 546,
            "pct": 55.9
          },
          {
            "level": "Some of the time",
            "count": 262,
            "pct": 26.8
          },
          {
            "level": "Much of the time",
            "count": 96,
            "pct": 9.8
          },
          {
            "level": "Most or all of the time",
            "count": 71,
            "pct": 7.3
          },
          {
            "level": "(Missing)",
            "count": 1,
            "pct": 0.1
          }
        ]
      },
      {
        "label": "race: 5 · sex: 1",
        "n": 859,
        "missing": 0,
        "n_levels": 4,
        "mode_level": "\"Rarely or none of the time\"",
        "freq": [
          {
            "level": "\"Rarely or none of the time\"",
            "count": 559,
            "pct": 65.1
          },
          {
            "level": "Some of the time",
            "count": 247,
            "pct": 28.8
          },
          {
            "level": "Much of the time",
            "count": 38,
            "pct": 4.4
          },
          {
            "level": "Most or all of the time",
            "count": 15,
            "pct": 1.7
          }
        ]
      },
      {
        "label": "race: 5 · sex: 2",
        "n": 991,
        "missing": 1,
        "n_levels": 5,
        "mode_level": "\"Rarely or none of the time\"",
        "freq": [
          {
            "level": "\"Rarely or none of the time\"",
            "count": 638,
            "pct": 64.4
          },
          {
            "level": "Some of the time",
            "count": 280,
            "pct": 28.3
          },
          {
            "level": "Much of the time",
            "count": 47,
            "pct": 4.7
          },
          {
            "level": "Most or all of the time",
            "count": 25,
            "pct": 2.5
          },
          {
            "level": "(Missing)",
            "count": 1,
            "pct": 0.1
          }
        ]
      }
    ],
    "sex_center": [
      {
        "label": "sex: 1 · center: 1",
        "n": 378,
        "missing": 0,
        "n_levels": 4,
        "mode_level": "\"Rarely or none of the time\"",
        "freq": [
          {
            "level": "\"Rarely or none of the time\"",
            "count": 219,
            "pct": 57.9
          },
          {
            "level": "Some of the time",
            "count": 104,
            "pct": 27.5
          },
          {
            "level": "Most or all of the time",
            "count": 28,
            "pct": 7.4
          },
          {
            "level": "Much of the time",
            "count": 27,
            "pct": 7.1
          }
        ]
      },
      {
        "label": "sex: 1 · center: 2",
        "n": 338,
        "missing": 0,
        "n_levels": 4,
        "mode_level": "\"Rarely or none of the time\"",
        "freq": [
          {
            "level": "\"Rarely or none of the time\"",
            "count": 205,
            "pct": 60.7
          },
          {
            "level": "Some of the time",
            "count": 100,
            "pct": 29.6
          },
          {
            "level": "Much of the time",
            "count": 22,
            "pct": 6.5
          },
          {
            "level": "Most or all of the time",
            "count": 11,
            "pct": 3.3
          }
        ]
      },
      {
        "label": "sex: 1 · center: 3",
        "n": 417,
        "missing": 0,
        "n_levels": 4,
        "mode_level": "\"Rarely or none of the time\"",
        "freq": [
          {
            "level": "\"Rarely or none of the time\"",
            "count": 252,
            "pct": 60.4
          },
          {
            "level": "Some of the time",
            "count": 131,
            "pct": 31.4
          },
          {
            "level": "Much of the time",
            "count": 25,
            "pct": 6
          },
          {
            "level": "Most or all of the time",
            "count": 9,
            "pct": 2.2
          }
        ]
      },
      {
        "label": "sex: 1 · center: 4",
        "n": 374,
        "missing": 0,
        "n_levels": 4,
        "mode_level": "\"Rarely or none of the time\"",
        "freq": [
          {
            "level": "\"Rarely or none of the time\"",
            "count": 217,
            "pct": 58
          },
          {
            "level": "Some of the time",
            "count": 113,
            "pct": 30.2
          },
          {
            "level": "Much of the time",
            "count": 26,
            "pct": 7
          },
          {
            "level": "Most or all of the time",
            "count": 18,
            "pct": 4.8
          }
        ]
      },
      {
        "label": "sex: 2 · center: 1",
        "n": 439,
        "missing": 1,
        "n_levels": 5,
        "mode_level": "\"Rarely or none of the time\"",
        "freq": [
          {
            "level": "\"Rarely or none of the time\"",
            "count": 265,
            "pct": 60.4
          },
          {
            "level": "Some of the time",
            "count": 113,
            "pct": 25.7
          },
          {
            "level": "Most or all of the time",
            "count": 32,
            "pct": 7.3
          },
          {
            "level": "Much of the time",
            "count": 28,
            "pct": 6.4
          },
          {
            "level": "(Missing)",
            "count": 1,
            "pct": 0.2
          }
        ]
      },
      {
        "label": "sex: 2 · center: 2",
        "n": 449,
        "missing": 0,
        "n_levels": 4,
        "mode_level": "\"Rarely or none of the time\"",
        "freq": [
          {
            "level": "\"Rarely or none of the time\"",
            "count": 259,
            "pct": 57.7
          },
          {
            "level": "Some of the time",
            "count": 122,
            "pct": 27.2
          },
          {
            "level": "Much of the time",
            "count": 44,
            "pct": 9.8
          },
          {
            "level": "Most or all of the time",
            "count": 24,
            "pct": 5.3
          }
        ]
      },
      {
        "label": "sex: 2 · center: 3",
        "n": 498,
        "missing": 1,
        "n_levels": 5,
        "mode_level": "\"Rarely or none of the time\"",
        "freq": [
          {
            "level": "\"Rarely or none of the time\"",
            "count": 307,
            "pct": 61.6
          },
          {
            "level": "Some of the time",
            "count": 139,
            "pct": 27.9
          },
          {
            "level": "Much of the time",
            "count": 30,
            "pct": 6
          },
          {
            "level": "Most or all of the time",
            "count": 21,
            "pct": 4.2
          },
          {
            "level": "(Missing)",
            "count": 1,
            "pct": 0.2
          }
        ]
      },
      {
        "label": "sex: 2 · center: 4",
        "n": 581,
        "missing": 0,
        "n_levels": 4,
        "mode_level": "\"Rarely or none of the time\"",
        "freq": [
          {
            "level": "\"Rarely or none of the time\"",
            "count": 353,
            "pct": 60.8
          },
          {
            "level": "Some of the time",
            "count": 168,
            "pct": 28.9
          },
          {
            "level": "Much of the time",
            "count": 41,
            "pct": 7.1
          },
          {
            "level": "Most or all of the time",
            "count": 19,
            "pct": 3.3
          }
        ]
      }
    ],
    "race_center": [
      {
        "label": "race: 4 · center: 1",
        "n": 455,
        "missing": 0,
        "n_levels": 4,
        "mode_level": "\"Rarely or none of the time\"",
        "freq": [
          {
            "level": "\"Rarely or none of the time\"",
            "count": 264,
            "pct": 58
          },
          {
            "level": "Some of the time",
            "count": 109,
            "pct": 24
          },
          {
            "level": "Most or all of the time",
            "count": 48,
            "pct": 10.5
          },
          {
            "level": "Much of the time",
            "count": 34,
            "pct": 7.5
          }
        ]
      },
      {
        "label": "race: 4 · center: 2",
        "n": 358,
        "missing": 0,
        "n_levels": 4,
        "mode_level": "\"Rarely or none of the time\"",
        "freq": [
          {
            "level": "\"Rarely or none of the time\"",
            "count": 180,
            "pct": 50.3
          },
          {
            "level": "Some of the time",
            "count": 103,
            "pct": 28.8
          },
          {
            "level": "Much of the time",
            "count": 50,
            "pct": 14
          },
          {
            "level": "Most or all of the time",
            "count": 25,
            "pct": 7
          }
        ]
      },
      {
        "label": "race: 4 · center: 3",
        "n": 327,
        "missing": 1,
        "n_levels": 5,
        "mode_level": "\"Rarely or none of the time\"",
        "freq": [
          {
            "level": "\"Rarely or none of the time\"",
            "count": 158,
            "pct": 48.3
          },
          {
            "level": "Some of the time",
            "count": 115,
            "pct": 35.2
          },
          {
            "level": "Much of the time",
            "count": 31,
            "pct": 9.5
          },
          {
            "level": "Most or all of the time",
            "count": 22,
            "pct": 6.7
          },
          {
            "level": "(Missing)",
            "count": 1,
            "pct": 0.3
          }
        ]
      },
      {
        "label": "race: 4 · center: 4",
        "n": 484,
        "missing": 0,
        "n_levels": 4,
        "mode_level": "\"Rarely or none of the time\"",
        "freq": [
          {
            "level": "\"Rarely or none of the time\"",
            "count": 278,
            "pct": 57.4
          },
          {
            "level": "Some of the time",
            "count": 136,
            "pct": 28.1
          },
          {
            "level": "Much of the time",
            "count": 43,
            "pct": 8.9
          },
          {
            "level": "Most or all of the time",
            "count": 27,
            "pct": 5.6
          }
        ]
      },
      {
        "label": "race: 5 · center: 1",
        "n": 362,
        "missing": 1,
        "n_levels": 5,
        "mode_level": "\"Rarely or none of the time\"",
        "freq": [
          {
            "level": "\"Rarely or none of the time\"",
            "count": 220,
            "pct": 60.8
          },
          {
            "level": "Some of the time",
            "count": 108,
            "pct": 29.8
          },
          {
            "level": "Much of the time",
            "count": 21,
            "pct": 5.8
          },
          {
            "level": "Most or all of the time",
            "count": 12,
            "pct": 3.3
          },
          {
            "level": "(Missing)",
            "count": 1,
            "pct": 0.3
          }
        ]
      },
      {
        "label": "race: 5 · center: 2",
        "n": 429,
        "missing": 0,
        "n_levels": 4,
        "mode_level": "\"Rarely or none of the time\"",
        "freq": [
          {
            "level": "\"Rarely or none of the time\"",
            "count": 284,
            "pct": 66.2
          },
          {
            "level": "Some of the time",
            "count": 119,
            "pct": 27.7
          },
          {
            "level": "Much of the time",
            "count": 16,
            "pct": 3.7
          },
          {
            "level": "Most or all of the time",
            "count": 10,
            "pct": 2.3
          }
        ]
      },
      {
        "label": "race: 5 · center: 3",
        "n": 588,
        "missing": 0,
        "n_levels": 4,
        "mode_level": "\"Rarely or none of the time\"",
        "freq": [
          {
            "level": "\"Rarely or none of the time\"",
            "count": 401,
            "pct": 68.2
          },
          {
            "level": "Some of the time",
            "count": 155,
            "pct": 26.4
          },
          {
            "level": "Much of the time",
            "count": 24,
            "pct": 4.1
          },
          {
            "level": "Most or all of the time",
            "count": 8,
            "pct": 1.4
          }
        ]
      },
      {
        "label": "race: 5 · center: 4",
        "n": 471,
        "missing": 0,
        "n_levels": 4,
        "mode_level": "\"Rarely or none of the time\"",
        "freq": [
          {
            "level": "\"Rarely or none of the time\"",
            "count": 292,
            "pct": 62
          },
          {
            "level": "Some of the time",
            "count": 145,
            "pct": 30.8
          },
          {
            "level": "Much of the time",
            "count": 24,
            "pct": 5.1
          },
          {
            "level": "Most or all of the time",
            "count": 10,
            "pct": 2.1
          }
        ]
      }
    ],
    "race_sex_center": [
      {
        "label": "race: 4 · sex: 1 · center: 1",
        "n": 189,
        "missing": 0,
        "n_levels": 4,
        "mode_level": "\"Rarely or none of the time\"",
        "freq": [
          {
            "level": "\"Rarely or none of the time\"",
            "count": 105,
            "pct": 55.6
          },
          {
            "level": "Some of the time",
            "count": 45,
            "pct": 23.8
          },
          {
            "level": "Most or all of the time",
            "count": 22,
            "pct": 11.6
          },
          {
            "level": "Much of the time",
            "count": 17,
            "pct": 9
          }
        ]
      },
      {
        "label": "race: 4 · sex: 1 · center: 2",
        "n": 131,
        "missing": 0,
        "n_levels": 4,
        "mode_level": "\"Rarely or none of the time\"",
        "freq": [
          {
            "level": "\"Rarely or none of the time\"",
            "count": 62,
            "pct": 47.3
          },
          {
            "level": "Some of the time",
            "count": 45,
            "pct": 34.4
          },
          {
            "level": "Much of the time",
            "count": 15,
            "pct": 11.5
          },
          {
            "level": "Most or all of the time",
            "count": 9,
            "pct": 6.9
          }
        ]
      },
      {
        "label": "race: 4 · sex: 1 · center: 3",
        "n": 143,
        "missing": 0,
        "n_levels": 4,
        "mode_level": "\"Rarely or none of the time\"",
        "freq": [
          {
            "level": "\"Rarely or none of the time\"",
            "count": 70,
            "pct": 49
          },
          {
            "level": "Some of the time",
            "count": 53,
            "pct": 37.1
          },
          {
            "level": "Much of the time",
            "count": 13,
            "pct": 9.1
          },
          {
            "level": "Most or all of the time",
            "count": 7,
            "pct": 4.9
          }
        ]
      },
      {
        "label": "race: 4 · sex: 1 · center: 4",
        "n": 185,
        "missing": 0,
        "n_levels": 4,
        "mode_level": "\"Rarely or none of the time\"",
        "freq": [
          {
            "level": "\"Rarely or none of the time\"",
            "count": 97,
            "pct": 52.4
          },
          {
            "level": "Some of the time",
            "count": 58,
            "pct": 31.4
          },
          {
            "level": "Much of the time",
            "count": 17,
            "pct": 9.2
          },
          {
            "level": "Most or all of the time",
            "count": 13,
            "pct": 7
          }
        ]
      },
      {
        "label": "race: 4 · sex: 2 · center: 1",
        "n": 266,
        "missing": 0,
        "n_levels": 4,
        "mode_level": "\"Rarely or none of the time\"",
        "freq": [
          {
            "level": "\"Rarely or none of the time\"",
            "count": 159,
            "pct": 59.8
          },
          {
            "level": "Some of the time",
            "count": 64,
            "pct": 24.1
          },
          {
            "level": "Most or all of the time",
            "count": 26,
            "pct": 9.8
          },
          {
            "level": "Much of the time",
            "count": 17,
            "pct": 6.4
          }
        ]
      },
      {
        "label": "race: 4 · sex: 2 · center: 2",
        "n": 227,
        "missing": 0,
        "n_levels": 4,
        "mode_level": "\"Rarely or none of the time\"",
        "freq": [
          {
            "level": "\"Rarely or none of the time\"",
            "count": 118,
            "pct": 52
          },
          {
            "level": "Some of the time",
            "count": 58,
            "pct": 25.6
          },
          {
            "level": "Much of the time",
            "count": 35,
            "pct": 15.4
          },
          {
            "level": "Most or all of the time",
            "count": 16,
            "pct": 7
          }
        ]
      },
      {
        "label": "race: 4 · sex: 2 · center: 3",
        "n": 184,
        "missing": 1,
        "n_levels": 5,
        "mode_level": "\"Rarely or none of the time\"",
        "freq": [
          {
            "level": "\"Rarely or none of the time\"",
            "count": 88,
            "pct": 47.8
          },
          {
            "level": "Some of the time",
            "count": 62,
            "pct": 33.7
          },
          {
            "level": "Much of the time",
            "count": 18,
            "pct": 9.8
          },
          {
            "level": "Most or all of the time",
            "count": 15,
            "pct": 8.2
          },
          {
            "level": "(Missing)",
            "count": 1,
            "pct": 0.5
          }
        ]
      },
      {
        "label": "race: 4 · sex: 2 · center: 4",
        "n": 299,
        "missing": 0,
        "n_levels": 4,
        "mode_level": "\"Rarely or none of the time\"",
        "freq": [
          {
            "level": "\"Rarely or none of the time\"",
            "count": 181,
            "pct": 60.5
          },
          {
            "level": "Some of the time",
            "count": 78,
            "pct": 26.1
          },
          {
            "level": "Much of the time",
            "count": 26,
            "pct": 8.7
          },
          {
            "level": "Most or all of the time",
            "count": 14,
            "pct": 4.7
          }
        ]
      },
      {
        "label": "race: 5 · sex: 1 · center: 1",
        "n": 189,
        "missing": 0,
        "n_levels": 4,
        "mode_level": "\"Rarely or none of the time\"",
        "freq": [
          {
            "level": "\"Rarely or none of the time\"",
            "count": 114,
            "pct": 60.3
          },
          {
            "level": "Some of the time",
            "count": 59,
            "pct": 31.2
          },
          {
            "level": "Much of the time",
            "count": 10,
            "pct": 5.3
          },
          {
            "level": "Most or all of the time",
            "count": 6,
            "pct": 3.2
          }
        ]
      },
      {
        "label": "race: 5 · sex: 1 · center: 2",
        "n": 207,
        "missing": 0,
        "n_levels": 4,
        "mode_level": "\"Rarely or none of the time\"",
        "freq": [
          {
            "level": "\"Rarely or none of the time\"",
            "count": 143,
            "pct": 69.1
          },
          {
            "level": "Some of the time",
            "count": 55,
            "pct": 26.6
          },
          {
            "level": "Much of the time",
            "count": 7,
            "pct": 3.4
          },
          {
            "level": "Most or all of the time",
            "count": 2,
            "pct": 1
          }
        ]
      },
      {
        "label": "race: 5 · sex: 1 · center: 3",
        "n": 274,
        "missing": 0,
        "n_levels": 4,
        "mode_level": "\"Rarely or none of the time\"",
        "freq": [
          {
            "level": "\"Rarely or none of the time\"",
            "count": 182,
            "pct": 66.4
          },
          {
            "level": "Some of the time",
            "count": 78,
            "pct": 28.5
          },
          {
            "level": "Much of the time",
            "count": 12,
            "pct": 4.4
          },
          {
            "level": "Most or all of the time",
            "count": 2,
            "pct": 0.7
          }
        ]
      },
      {
        "label": "race: 5 · sex: 1 · center: 4",
        "n": 189,
        "missing": 0,
        "n_levels": 4,
        "mode_level": "\"Rarely or none of the time\"",
        "freq": [
          {
            "level": "\"Rarely or none of the time\"",
            "count": 120,
            "pct": 63.5
          },
          {
            "level": "Some of the time",
            "count": 55,
            "pct": 29.1
          },
          {
            "level": "Much of the time",
            "count": 9,
            "pct": 4.8
          },
          {
            "level": "Most or all of the time",
            "count": 5,
            "pct": 2.6
          }
        ]
      },
      {
        "label": "race: 5 · sex: 2 · center: 1",
        "n": 173,
        "missing": 1,
        "n_levels": 5,
        "mode_level": "\"Rarely or none of the time\"",
        "freq": [
          {
            "level": "\"Rarely or none of the time\"",
            "count": 106,
            "pct": 61.3
          },
          {
            "level": "Some of the time",
            "count": 49,
            "pct": 28.3
          },
          {
            "level": "Much of the time",
            "count": 11,
            "pct": 6.4
          },
          {
            "level": "Most or all of the time",
            "count": 6,
            "pct": 3.5
          },
          {
            "level": "(Missing)",
            "count": 1,
            "pct": 0.6
          }
        ]
      },
      {
        "label": "race: 5 · sex: 2 · center: 2",
        "n": 222,
        "missing": 0,
        "n_levels": 4,
        "mode_level": "\"Rarely or none of the time\"",
        "freq": [
          {
            "level": "\"Rarely or none of the time\"",
            "count": 141,
            "pct": 63.5
          },
          {
            "level": "Some of the time",
            "count": 64,
            "pct": 28.8
          },
          {
            "level": "Much of the time",
            "count": 9,
            "pct": 4.1
          },
          {
            "level": "Most or all of the time",
            "count": 8,
            "pct": 3.6
          }
        ]
      },
      {
        "label": "race: 5 · sex: 2 · center: 3",
        "n": 314,
        "missing": 0,
        "n_levels": 4,
        "mode_level": "\"Rarely or none of the time\"",
        "freq": [
          {
            "level": "\"Rarely or none of the time\"",
            "count": 219,
            "pct": 69.7
          },
          {
            "level": "Some of the time",
            "count": 77,
            "pct": 24.5
          },
          {
            "level": "Much of the time",
            "count": 12,
            "pct": 3.8
          },
          {
            "level": "Most or all of the time",
            "count": 6,
            "pct": 1.9
          }
        ]
      },
      {
        "label": "race: 5 · sex: 2 · center: 4",
        "n": 282,
        "missing": 0,
        "n_levels": 4,
        "mode_level": "\"Rarely or none of the time\"",
        "freq": [
          {
            "level": "\"Rarely or none of the time\"",
            "count": 172,
            "pct": 61
          },
          {
            "level": "Some of the time",
            "count": 90,
            "pct": 31.9
          },
          {
            "level": "Much of the time",
            "count": 15,
            "pct": 5.3
          },
          {
            "level": "Most or all of the time",
            "count": 5,
            "pct": 1.8
          }
        ]
      }
    ]
  }
}
