{
  "concept_id": "IMAGES_RECEIVED_COUNT",
  "exam": "G",
  "by": {
    "all": [
      {
        "label": "All",
        "n": 3139,
        "missing": 0,
        "mean": 44.8321,
        "sd": 5.8263,
        "p05": 37,
        "q1": 40,
        "median": 45,
        "q3": 48,
        "p95": 56,
        "iqr": 8
      }
    ],
    "sex": [
      {
        "label": "sex: 1",
        "n": 1354,
        "missing": 0,
        "mean": 45.5997,
        "sd": 6.152,
        "p05": 37,
        "q1": 40,
        "median": 48,
        "q3": 48,
        "p95": 56,
        "iqr": 8
      },
      {
        "label": "sex: 2",
        "n": 1785,
        "missing": 0,
        "mean": 44.2499,
        "sd": 5.4973,
        "p05": 37,
        "q1": 40,
        "median": 43,
        "q3": 48,
        "p95": 56,
        "iqr": 8
      }
    ],
    "race": [
      {
        "label": "race: 4",
        "n": 1411,
        "missing": 0,
        "mean": 43.9674,
        "sd": 5.5698,
        "p05": 36,
        "q1": 40,
        "median": 42,
        "q3": 48,
        "p95": 56,
        "iqr": 8
      },
      {
        "label": "race: 5",
        "n": 1728,
        "missing": 0,
        "mean": 45.5382,
        "sd": 5.9365,
        "p05": 38.35,
        "q1": 40,
        "median": 47,
        "q3": 48,
        "p95": 56,
        "iqr": 8
      }
    ],
    "center": [
      {
        "label": "center: 1",
        "n": 738,
        "missing": 0,
        "mean": 50.252,
        "sd": 5.0265,
        "p05": 40,
        "q1": 48,
        "median": 48,
        "q3": 56,
        "p95": 56,
        "iqr": 8
      },
      {
        "label": "center: 2",
        "n": 713,
        "missing": 0,
        "mean": 40.1641,
        "sd": 1.0289,
        "p05": 40,
        "q1": 40,
        "median": 40,
        "q3": 40,
        "p95": 40,
        "iqr": 0
      },
      {
        "label": "center: 3",
        "n": 840,
        "missing": 0,
        "mean": 47.7429,
        "sd": 4.0856,
        "p05": 42,
        "q1": 48,
        "median": 48,
        "q3": 48,
        "p95": 54,
        "iqr": 0
      },
      {
        "label": "center: 4",
        "n": 848,
        "missing": 0,
        "mean": 41.1568,
        "sd": 4.5267,
        "p05": 35,
        "q1": 38,
        "median": 41,
        "q3": 44,
        "p95": 49,
        "iqr": 6
      }
    ],
    "race_sex": [
      {
        "label": "race: 4 · sex: 1",
        "n": 547,
        "missing": 0,
        "mean": 45.0859,
        "sd": 6.0233,
        "p05": 36,
        "q1": 40,
        "median": 46,
        "q3": 48,
        "p95": 56,
        "iqr": 8
      },
      {
        "label": "race: 4 · sex: 2",
        "n": 864,
        "missing": 0,
        "mean": 43.2593,
        "sd": 5.1418,
        "p05": 36,
        "q1": 40,
        "median": 41,
        "q3": 48,
        "p95": 54,
        "iqr": 8
      },
      {
        "label": "race: 5 · sex: 1",
        "n": 807,
        "missing": 0,
        "mean": 45.948,
        "sd": 6.2173,
        "p05": 39,
        "q1": 40,
        "median": 48,
        "q3": 48,
        "p95": 56,
        "iqr": 8
      },
      {
        "label": "race: 5 · sex: 2",
        "n": 921,
        "missing": 0,
        "mean": 45.1792,
        "sd": 5.6581,
        "p05": 38,
        "q1": 40,
        "median": 46,
        "q3": 48,
        "p95": 56,
        "iqr": 8
      }
    ],
    "sex_center": [
      {
        "label": "sex: 1 · center: 1",
        "n": 339,
        "missing": 0,
        "mean": 51.3156,
        "sd": 5.0257,
        "p05": 48,
        "q1": 48,
        "median": 48,
        "q3": 56,
        "p95": 56,
        "iqr": 8
      },
      {
        "label": "sex: 1 · center: 2",
        "n": 308,
        "missing": 0,
        "mean": 40.1883,
        "sd": 0.9222,
        "p05": 40,
        "q1": 40,
        "median": 40,
        "q3": 40,
        "p95": 40,
        "iqr": 0
      },
      {
        "label": "sex: 1 · center: 3",
        "n": 384,
        "missing": 0,
        "mean": 48.4557,
        "sd": 4.3084,
        "p05": 42,
        "q1": 48,
        "median": 48,
        "q3": 48,
        "p95": 54,
        "iqr": 0
      },
      {
        "label": "sex: 1 · center: 4",
        "n": 323,
        "missing": 0,
        "mean": 41.3653,
        "sd": 4.4165,
        "p05": 35,
        "q1": 38,
        "median": 41,
        "q3": 44,
        "p95": 49,
        "iqr": 6
      },
      {
        "label": "sex: 2 · center: 1",
        "n": 399,
        "missing": 0,
        "mean": 49.3484,
        "sd": 4.8533,
        "p05": 40,
        "q1": 48,
        "median": 48,
        "q3": 56,
        "p95": 56,
        "iqr": 8
      },
      {
        "label": "sex: 2 · center: 2",
        "n": 405,
        "missing": 0,
        "mean": 40.1457,
        "sd": 1.104,
        "p05": 40,
        "q1": 40,
        "median": 40,
        "q3": 40,
        "p95": 40,
        "iqr": 0
      },
      {
        "label": "sex: 2 · center: 3",
        "n": 456,
        "missing": 0,
        "mean": 47.1425,
        "sd": 3.79,
        "p05": 42,
        "q1": 48,
        "median": 48,
        "q3": 48,
        "p95": 54,
        "iqr": 0
      },
      {
        "label": "sex: 2 · center: 4",
        "n": 525,
        "missing": 0,
        "mean": 41.0286,
        "sd": 4.5927,
        "p05": 35,
        "q1": 38,
        "median": 41,
        "q3": 44,
        "p95": 48.8,
        "iqr": 6
      }
    ],
    "race_center": [
      {
        "label": "race: 4 · center: 1",
        "n": 389,
        "missing": 0,
        "mean": 49.1105,
        "sd": 4.8141,
        "p05": 40,
        "q1": 48,
        "median": 48,
        "q3": 48,
        "p95": 56,
        "iqr": 0
      },
      {
        "label": "race: 4 · center: 2",
        "n": 322,
        "missing": 0,
        "mean": 40.0901,
        "sd": 0.6707,
        "p05": 40,
        "q1": 40,
        "median": 40,
        "q3": 40,
        "p95": 40,
        "iqr": 0
      },
      {
        "label": "race: 4 · center: 3",
        "n": 283,
        "missing": 0,
        "mean": 47.1943,
        "sd": 3.5572,
        "p05": 42,
        "q1": 48,
        "median": 48,
        "q3": 48,
        "p95": 54,
        "iqr": 0
      },
      {
        "label": "race: 4 · center: 4",
        "n": 417,
        "missing": 0,
        "mean": 39.9736,
        "sd": 3.8942,
        "p05": 34,
        "q1": 37,
        "median": 40,
        "q3": 42,
        "p95": 47,
        "iqr": 5
      },
      {
        "label": "race: 5 · center: 1",
        "n": 349,
        "missing": 0,
        "mean": 51.5244,
        "sd": 4.9588,
        "p05": 48,
        "q1": 48,
        "median": 48,
        "q3": 56,
        "p95": 56,
        "iqr": 8
      },
      {
        "label": "race: 5 · center: 2",
        "n": 391,
        "missing": 0,
        "mean": 40.2251,
        "sd": 1.2467,
        "p05": 40,
        "q1": 40,
        "median": 40,
        "q3": 40,
        "p95": 40,
        "iqr": 0
      },
      {
        "label": "race: 5 · center: 3",
        "n": 557,
        "missing": 0,
        "mean": 48.0215,
        "sd": 4.3057,
        "p05": 41,
        "q1": 48,
        "median": 48,
        "q3": 48,
        "p95": 54,
        "iqr": 0
      },
      {
        "label": "race: 5 · center: 4",
        "n": 431,
        "missing": 0,
        "mean": 42.3016,
        "sd": 4.798,
        "p05": 35.5,
        "q1": 40,
        "median": 42,
        "q3": 45,
        "p95": 50,
        "iqr": 5
      }
    ],
    "race_sex_center": [
      {
        "label": "race: 4 · sex: 1 · center: 1",
        "n": 152,
        "missing": 0,
        "mean": 51,
        "sd": 4.7674,
        "p05": 48,
        "q1": 48,
        "median": 48,
        "q3": 56,
        "p95": 56,
        "iqr": 8
      },
      {
        "label": "race: 4 · sex: 1 · center: 2",
        "n": 118,
        "missing": 0,
        "mean": 40.161,
        "sd": 0.8056,
        "p05": 40,
        "q1": 40,
        "median": 40,
        "q3": 40,
        "p95": 40,
        "iqr": 0
      },
      {
        "label": "race: 4 · sex: 1 · center: 3",
        "n": 125,
        "missing": 0,
        "mean": 48.08,
        "sd": 3.1253,
        "p05": 42,
        "q1": 48,
        "median": 48,
        "q3": 48,
        "p95": 54,
        "iqr": 0
      },
      {
        "label": "race: 4 · sex: 1 · center: 4",
        "n": 152,
        "missing": 0,
        "mean": 40.5329,
        "sd": 4.1812,
        "p05": 34.55,
        "q1": 37,
        "median": 40,
        "q3": 43,
        "p95": 48,
        "iqr": 6
      },
      {
        "label": "race: 4 · sex: 2 · center: 1",
        "n": 237,
        "missing": 0,
        "mean": 47.8987,
        "sd": 4.4482,
        "p05": 40,
        "q1": 48,
        "median": 48,
        "q3": 48,
        "p95": 56,
        "iqr": 0
      },
      {
        "label": "race: 4 · sex: 2 · center: 2",
        "n": 204,
        "missing": 0,
        "mean": 40.049,
        "sd": 0.5767,
        "p05": 40,
        "q1": 40,
        "median": 40,
        "q3": 40,
        "p95": 40,
        "iqr": 0
      },
      {
        "label": "race: 4 · sex: 2 · center: 3",
        "n": 158,
        "missing": 0,
        "mean": 46.4937,
        "sd": 3.7276,
        "p05": 42,
        "q1": 42,
        "median": 48,
        "q3": 48,
        "p95": 54,
        "iqr": 6
      },
      {
        "label": "race: 4 · sex: 2 · center: 4",
        "n": 265,
        "missing": 0,
        "mean": 39.6528,
        "sd": 3.6897,
        "p05": 34,
        "q1": 37,
        "median": 40,
        "q3": 42,
        "p95": 46,
        "iqr": 5
      },
      {
        "label": "race: 5 · sex: 1 · center: 1",
        "n": 187,
        "missing": 0,
        "mean": 51.5722,
        "sd": 5.2249,
        "p05": 48,
        "q1": 48,
        "median": 48,
        "q3": 56,
        "p95": 56,
        "iqr": 8
      },
      {
        "label": "race: 5 · sex: 1 · center: 2",
        "n": 190,
        "missing": 0,
        "mean": 40.2053,
        "sd": 0.9893,
        "p05": 40,
        "q1": 40,
        "median": 40,
        "q3": 40,
        "p95": 41.1,
        "iqr": 0
      },
      {
        "label": "race: 5 · sex: 1 · center: 3",
        "n": 259,
        "missing": 0,
        "mean": 48.6371,
        "sd": 4.7707,
        "p05": 40,
        "q1": 48,
        "median": 48,
        "q3": 48,
        "p95": 54,
        "iqr": 0
      },
      {
        "label": "race: 5 · sex: 1 · center: 4",
        "n": 171,
        "missing": 0,
        "mean": 42.1053,
        "sd": 4.4997,
        "p05": 35,
        "q1": 40,
        "median": 42,
        "q3": 45,
        "p95": 50,
        "iqr": 5
      },
      {
        "label": "race: 5 · sex: 2 · center: 1",
        "n": 162,
        "missing": 0,
        "mean": 51.4691,
        "sd": 4.6481,
        "p05": 48,
        "q1": 48,
        "median": 48,
        "q3": 56,
        "p95": 56,
        "iqr": 8
      },
      {
        "label": "race: 5 · sex: 2 · center: 2",
        "n": 201,
        "missing": 0,
        "mean": 40.2438,
        "sd": 1.451,
        "p05": 40,
        "q1": 40,
        "median": 40,
        "q3": 40,
        "p95": 40,
        "iqr": 0
      },
      {
        "label": "race: 5 · sex: 2 · center: 3",
        "n": 298,
        "missing": 0,
        "mean": 47.4866,
        "sd": 3.7839,
        "p05": 42,
        "q1": 48,
        "median": 48,
        "q3": 48,
        "p95": 54,
        "iqr": 0
      },
      {
        "label": "race: 5 · sex: 2 · center: 4",
        "n": 260,
        "missing": 0,
        "mean": 42.4308,
        "sd": 4.9887,
        "p05": 36,
        "q1": 40,
        "median": 42,
        "q3": 45,
        "p95": 50,
        "iqr": 5
      }
    ]
  }
}
