{
  "concept_id": "NUMBER_OF_DOCTOR_VISITS_PAST_YEAR",
  "title": "Number of Doctor or Clinic Visits in Past Year",
  "unit": {},
  "chips": ["numeric", "Medical History"],
  "members": [
    {
      "concept_id": "NUMBER_OF_DOCTOR_VISITS_PAST_YEAR",
      "exam": "D",
      "exam_year": "",
      "dataset": "dflwup1",
      "dataset_stub": "dflwup1",
      "varname": "FY108OTX",
      "family": "FLWUP",
      "form_label": "",
      "units_std": "",
      "units_class": "",
      "instrument": "FLWUP",
      "notes": ""
    }
  ]
}
