{
  "concept_id": "OPTIMISM_IF_WRONG_IT_WILL",
  "exam": "F",
  "by": {
    "all": [
      {
        "label": "All",
        "n": 3671,
        "missing": 15,
        "n_levels": 6,
        "mode_level": "Disagree",
        "freq": [
          {
            "level": "Disagree",
            "count": 1906,
            "pct": 51.9
          },
          {
            "level": "Neutral",
            "count": 796,
            "pct": 21.7
          },
          {
            "level": "Strongly disagree",
            "count": 521,
            "pct": 14.2
          },
          {
            "level": "Agree",
            "count": 388,
            "pct": 10.6
          },
          {
            "level": "Strongly agree",
            "count": 45,
            "pct": 1.2
          },
          {
            "level": "(Missing)",
            "count": 15,
            "pct": 0.4
          }
        ]
      }
    ],
    "sex": [
      {
        "label": "sex: 1",
        "n": 1619,
        "missing": 7,
        "n_levels": 6,
        "mode_level": "Disagree",
        "freq": [
          {
            "level": "Disagree",
            "count": 843,
            "pct": 52.1
          },
          {
            "level": "Neutral",
            "count": 375,
            "pct": 23.2
          },
          {
            "level": "Strongly disagree",
            "count": 200,
            "pct": 12.4
          },
          {
            "level": "Agree",
            "count": 173,
            "pct": 10.7
          },
          {
            "level": "Strongly agree",
            "count": 21,
            "pct": 1.3
          },
          {
            "level": "(Missing)",
            "count": 7,
            "pct": 0.4
          }
        ]
      },
      {
        "label": "sex: 2",
        "n": 2052,
        "missing": 8,
        "n_levels": 6,
        "mode_level": "Disagree",
        "freq": [
          {
            "level": "Disagree",
            "count": 1063,
            "pct": 51.8
          },
          {
            "level": "Neutral",
            "count": 421,
            "pct": 20.5
          },
          {
            "level": "Strongly disagree",
            "count": 321,
            "pct": 15.6
          },
          {
            "level": "Agree",
            "count": 215,
            "pct": 10.5
          },
          {
            "level": "Strongly agree",
            "count": 24,
            "pct": 1.2
          },
          {
            "level": "(Missing)",
            "count": 8,
            "pct": 0.4
          }
        ]
      }
    ],
    "race": [
      {
        "label": "race: 4",
        "n": 1730,
        "missing": 7,
        "n_levels": 6,
        "mode_level": "Disagree",
        "freq": [
          {
            "level": "Disagree",
            "count": 776,
            "pct": 44.9
          },
          {
            "level": "Neutral",
            "count": 429,
            "pct": 24.8
          },
          {
            "level": "Agree",
            "count": 258,
            "pct": 14.9
          },
          {
            "level": "Strongly disagree",
            "count": 229,
            "pct": 13.2
          },
          {
            "level": "Strongly agree",
            "count": 31,
            "pct": 1.8
          },
          {
            "level": "(Missing)",
            "count": 7,
            "pct": 0.4
          }
        ]
      },
      {
        "label": "race: 5",
        "n": 1941,
        "missing": 8,
        "n_levels": 6,
        "mode_level": "Disagree",
        "freq": [
          {
            "level": "Disagree",
            "count": 1130,
            "pct": 58.2
          },
          {
            "level": "Neutral",
            "count": 367,
            "pct": 18.9
          },
          {
            "level": "Strongly disagree",
            "count": 292,
            "pct": 15
          },
          {
            "level": "Agree",
            "count": 130,
            "pct": 6.7
          },
          {
            "level": "Strongly agree",
            "count": 14,
            "pct": 0.7
          },
          {
            "level": "(Missing)",
            "count": 8,
            "pct": 0.4
          }
        ]
      }
    ],
    "center": [
      {
        "label": "center: 1",
        "n": 858,
        "missing": 7,
        "n_levels": 6,
        "mode_level": "Disagree",
        "freq": [
          {
            "level": "Disagree",
            "count": 430,
            "pct": 50.1
          },
          {
            "level": "Neutral",
            "count": 182,
            "pct": 21.2
          },
          {
            "level": "Agree",
            "count": 119,
            "pct": 13.9
          },
          {
            "level": "Strongly disagree",
            "count": 109,
            "pct": 12.7
          },
          {
            "level": "Strongly agree",
            "count": 11,
            "pct": 1.3
          },
          {
            "level": "(Missing)",
            "count": 7,
            "pct": 0.8
          }
        ]
      },
      {
        "label": "center: 2",
        "n": 815,
        "missing": 0,
        "n_levels": 5,
        "mode_level": "Disagree",
        "freq": [
          {
            "level": "Disagree",
            "count": 395,
            "pct": 48.5
          },
          {
            "level": "Neutral",
            "count": 184,
            "pct": 22.6
          },
          {
            "level": "Strongly disagree",
            "count": 141,
            "pct": 17.3
          },
          {
            "level": "Agree",
            "count": 88,
            "pct": 10.8
          },
          {
            "level": "Strongly agree",
            "count": 7,
            "pct": 0.9
          }
        ]
      },
      {
        "label": "center: 3",
        "n": 993,
        "missing": 3,
        "n_levels": 6,
        "mode_level": "Disagree",
        "freq": [
          {
            "level": "Disagree",
            "count": 544,
            "pct": 54.8
          },
          {
            "level": "Neutral",
            "count": 196,
            "pct": 19.7
          },
          {
            "level": "Strongly disagree",
            "count": 135,
            "pct": 13.6
          },
          {
            "level": "Agree",
            "count": 98,
            "pct": 9.9
          },
          {
            "level": "Strongly agree",
            "count": 17,
            "pct": 1.7
          },
          {
            "level": "(Missing)",
            "count": 3,
            "pct": 0.3
          }
        ]
      },
      {
        "label": "center: 4",
        "n": 1005,
        "missing": 5,
        "n_levels": 6,
        "mode_level": "Disagree",
        "freq": [
          {
            "level": "Disagree",
            "count": 537,
            "pct": 53.4
          },
          {
            "level": "Neutral",
            "count": 234,
            "pct": 23.3
          },
          {
            "level": "Strongly disagree",
            "count": 136,
            "pct": 13.5
          },
          {
            "level": "Agree",
            "count": 83,
            "pct": 8.3
          },
          {
            "level": "Strongly agree",
            "count": 10,
            "pct": 1
          },
          {
            "level": "(Missing)",
            "count": 5,
            "pct": 0.5
          }
        ]
      }
    ],
    "race_sex": [
      {
        "label": "race: 4 · sex: 1",
        "n": 709,
        "missing": 2,
        "n_levels": 6,
        "mode_level": "Disagree",
        "freq": [
          {
            "level": "Disagree",
            "count": 309,
            "pct": 43.6
          },
          {
            "level": "Neutral",
            "count": 201,
            "pct": 28.3
          },
          {
            "level": "Agree",
            "count": 105,
            "pct": 14.8
          },
          {
            "level": "Strongly disagree",
            "count": 77,
            "pct": 10.9
          },
          {
            "level": "Strongly agree",
            "count": 15,
            "pct": 2.1
          },
          {
            "level": "(Missing)",
            "count": 2,
            "pct": 0.3
          }
        ]
      },
      {
        "label": "race: 4 · sex: 2",
        "n": 1021,
        "missing": 5,
        "n_levels": 6,
        "mode_level": "Disagree",
        "freq": [
          {
            "level": "Disagree",
            "count": 467,
            "pct": 45.7
          },
          {
            "level": "Neutral",
            "count": 228,
            "pct": 22.3
          },
          {
            "level": "Agree",
            "count": 153,
            "pct": 15
          },
          {
            "level": "Strongly disagree",
            "count": 152,
            "pct": 14.9
          },
          {
            "level": "Strongly agree",
            "count": 16,
            "pct": 1.6
          },
          {
            "level": "(Missing)",
            "count": 5,
            "pct": 0.5
          }
        ]
      },
      {
        "label": "race: 5 · sex: 1",
        "n": 910,
        "missing": 5,
        "n_levels": 6,
        "mode_level": "Disagree",
        "freq": [
          {
            "level": "Disagree",
            "count": 534,
            "pct": 58.7
          },
          {
            "level": "Neutral",
            "count": 174,
            "pct": 19.1
          },
          {
            "level": "Strongly disagree",
            "count": 123,
            "pct": 13.5
          },
          {
            "level": "Agree",
            "count": 68,
            "pct": 7.5
          },
          {
            "level": "Strongly agree",
            "count": 6,
            "pct": 0.7
          },
          {
            "level": "(Missing)",
            "count": 5,
            "pct": 0.5
          }
        ]
      },
      {
        "label": "race: 5 · sex: 2",
        "n": 1031,
        "missing": 3,
        "n_levels": 6,
        "mode_level": "Disagree",
        "freq": [
          {
            "level": "Disagree",
            "count": 596,
            "pct": 57.8
          },
          {
            "level": "Neutral",
            "count": 193,
            "pct": 18.7
          },
          {
            "level": "Strongly disagree",
            "count": 169,
            "pct": 16.4
          },
          {
            "level": "Agree",
            "count": 62,
            "pct": 6
          },
          {
            "level": "Strongly agree",
            "count": 8,
            "pct": 0.8
          },
          {
            "level": "(Missing)",
            "count": 3,
            "pct": 0.3
          }
        ]
      }
    ],
    "sex_center": [
      {
        "label": "sex: 1 · center: 1",
        "n": 410,
        "missing": 5,
        "n_levels": 6,
        "mode_level": "Disagree",
        "freq": [
          {
            "level": "Disagree",
            "count": 195,
            "pct": 47.6
          },
          {
            "level": "Neutral",
            "count": 96,
            "pct": 23.4
          },
          {
            "level": "Agree",
            "count": 63,
            "pct": 15.4
          },
          {
            "level": "Strongly disagree",
            "count": 47,
            "pct": 11.5
          },
          {
            "level": "(Missing)",
            "count": 5,
            "pct": 1.2
          },
          {
            "level": "Strongly agree",
            "count": 4,
            "pct": 1
          }
        ]
      },
      {
        "label": "sex: 1 · center: 2",
        "n": 366,
        "missing": 0,
        "n_levels": 5,
        "mode_level": "Disagree",
        "freq": [
          {
            "level": "Disagree",
            "count": 181,
            "pct": 49.5
          },
          {
            "level": "Neutral",
            "count": 84,
            "pct": 23
          },
          {
            "level": "Strongly disagree",
            "count": 68,
            "pct": 18.6
          },
          {
            "level": "Agree",
            "count": 29,
            "pct": 7.9
          },
          {
            "level": "Strongly agree",
            "count": 4,
            "pct": 1.1
          }
        ]
      },
      {
        "label": "sex: 1 · center: 3",
        "n": 468,
        "missing": 1,
        "n_levels": 6,
        "mode_level": "Disagree",
        "freq": [
          {
            "level": "Disagree",
            "count": 257,
            "pct": 54.9
          },
          {
            "level": "Neutral",
            "count": 102,
            "pct": 21.8
          },
          {
            "level": "Agree",
            "count": 54,
            "pct": 11.5
          },
          {
            "level": "Strongly disagree",
            "count": 46,
            "pct": 9.8
          },
          {
            "level": "Strongly agree",
            "count": 8,
            "pct": 1.7
          },
          {
            "level": "(Missing)",
            "count": 1,
            "pct": 0.2
          }
        ]
      },
      {
        "label": "sex: 1 · center: 4",
        "n": 375,
        "missing": 1,
        "n_levels": 6,
        "mode_level": "Disagree",
        "freq": [
          {
            "level": "Disagree",
            "count": 210,
            "pct": 56
          },
          {
            "level": "Neutral",
            "count": 93,
            "pct": 24.8
          },
          {
            "level": "Strongly disagree",
            "count": 39,
            "pct": 10.4
          },
          {
            "level": "Agree",
            "count": 27,
            "pct": 7.2
          },
          {
            "level": "Strongly agree",
            "count": 5,
            "pct": 1.3
          },
          {
            "level": "(Missing)",
            "count": 1,
            "pct": 0.3
          }
        ]
      },
      {
        "label": "sex: 2 · center: 1",
        "n": 448,
        "missing": 2,
        "n_levels": 6,
        "mode_level": "Disagree",
        "freq": [
          {
            "level": "Disagree",
            "count": 235,
            "pct": 52.5
          },
          {
            "level": "Neutral",
            "count": 86,
            "pct": 19.2
          },
          {
            "level": "Strongly disagree",
            "count": 62,
            "pct": 13.8
          },
          {
            "level": "Agree",
            "count": 56,
            "pct": 12.5
          },
          {
            "level": "Strongly agree",
            "count": 7,
            "pct": 1.6
          },
          {
            "level": "(Missing)",
            "count": 2,
            "pct": 0.4
          }
        ]
      },
      {
        "label": "sex: 2 · center: 2",
        "n": 449,
        "missing": 0,
        "n_levels": 5,
        "mode_level": "Disagree",
        "freq": [
          {
            "level": "Disagree",
            "count": 214,
            "pct": 47.7
          },
          {
            "level": "Neutral",
            "count": 100,
            "pct": 22.3
          },
          {
            "level": "Strongly disagree",
            "count": 73,
            "pct": 16.3
          },
          {
            "level": "Agree",
            "count": 59,
            "pct": 13.1
          },
          {
            "level": "Strongly agree",
            "count": 3,
            "pct": 0.7
          }
        ]
      },
      {
        "label": "sex: 2 · center: 3",
        "n": 525,
        "missing": 2,
        "n_levels": 6,
        "mode_level": "Disagree",
        "freq": [
          {
            "level": "Disagree",
            "count": 287,
            "pct": 54.7
          },
          {
            "level": "Neutral",
            "count": 94,
            "pct": 17.9
          },
          {
            "level": "Strongly disagree",
            "count": 89,
            "pct": 17
          },
          {
            "level": "Agree",
            "count": 44,
            "pct": 8.4
          },
          {
            "level": "Strongly agree",
            "count": 9,
            "pct": 1.7
          },
          {
            "level": "(Missing)",
            "count": 2,
            "pct": 0.4
          }
        ]
      },
      {
        "label": "sex: 2 · center: 4",
        "n": 630,
        "missing": 4,
        "n_levels": 6,
        "mode_level": "Disagree",
        "freq": [
          {
            "level": "Disagree",
            "count": 327,
            "pct": 51.9
          },
          {
            "level": "Neutral",
            "count": 141,
            "pct": 22.4
          },
          {
            "level": "Strongly disagree",
            "count": 97,
            "pct": 15.4
          },
          {
            "level": "Agree",
            "count": 56,
            "pct": 8.9
          },
          {
            "level": "Strongly agree",
            "count": 5,
            "pct": 0.8
          },
          {
            "level": "(Missing)",
            "count": 4,
            "pct": 0.6
          }
        ]
      }
    ],
    "race_center": [
      {
        "label": "race: 4 · center: 1",
        "n": 478,
        "missing": 3,
        "n_levels": 6,
        "mode_level": "Disagree",
        "freq": [
          {
            "level": "Disagree",
            "count": 201,
            "pct": 42.1
          },
          {
            "level": "Neutral",
            "count": 109,
            "pct": 22.8
          },
          {
            "level": "Agree",
            "count": 91,
            "pct": 19
          },
          {
            "level": "Strongly disagree",
            "count": 65,
            "pct": 13.6
          },
          {
            "level": "Strongly agree",
            "count": 9,
            "pct": 1.9
          },
          {
            "level": "(Missing)",
            "count": 3,
            "pct": 0.6
          }
        ]
      },
      {
        "label": "race: 4 · center: 2",
        "n": 370,
        "missing": 0,
        "n_levels": 5,
        "mode_level": "Disagree",
        "freq": [
          {
            "level": "Disagree",
            "count": 156,
            "pct": 42.2
          },
          {
            "level": "Neutral",
            "count": 97,
            "pct": 26.2
          },
          {
            "level": "Strongly disagree",
            "count": 58,
            "pct": 15.7
          },
          {
            "level": "Agree",
            "count": 54,
            "pct": 14.6
          },
          {
            "level": "Strongly agree",
            "count": 5,
            "pct": 1.4
          }
        ]
      },
      {
        "label": "race: 4 · center: 3",
        "n": 355,
        "missing": 2,
        "n_levels": 6,
        "mode_level": "Disagree",
        "freq": [
          {
            "level": "Disagree",
            "count": 157,
            "pct": 44.2
          },
          {
            "level": "Neutral",
            "count": 89,
            "pct": 25.1
          },
          {
            "level": "Agree",
            "count": 57,
            "pct": 16.1
          },
          {
            "level": "Strongly disagree",
            "count": 41,
            "pct": 11.5
          },
          {
            "level": "Strongly agree",
            "count": 9,
            "pct": 2.5
          },
          {
            "level": "(Missing)",
            "count": 2,
            "pct": 0.6
          }
        ]
      },
      {
        "label": "race: 4 · center: 4",
        "n": 527,
        "missing": 2,
        "n_levels": 6,
        "mode_level": "Disagree",
        "freq": [
          {
            "level": "Disagree",
            "count": 262,
            "pct": 49.7
          },
          {
            "level": "Neutral",
            "count": 134,
            "pct": 25.4
          },
          {
            "level": "Strongly disagree",
            "count": 65,
            "pct": 12.3
          },
          {
            "level": "Agree",
            "count": 56,
            "pct": 10.6
          },
          {
            "level": "Strongly agree",
            "count": 8,
            "pct": 1.5
          },
          {
            "level": "(Missing)",
            "count": 2,
            "pct": 0.4
          }
        ]
      },
      {
        "label": "race: 5 · center: 1",
        "n": 380,
        "missing": 4,
        "n_levels": 6,
        "mode_level": "Disagree",
        "freq": [
          {
            "level": "Disagree",
            "count": 229,
            "pct": 60.3
          },
          {
            "level": "Neutral",
            "count": 73,
            "pct": 19.2
          },
          {
            "level": "Strongly disagree",
            "count": 44,
            "pct": 11.6
          },
          {
            "level": "Agree",
            "count": 28,
            "pct": 7.4
          },
          {
            "level": "(Missing)",
            "count": 4,
            "pct": 1.1
          },
          {
            "level": "Strongly agree",
            "count": 2,
            "pct": 0.5
          }
        ]
      },
      {
        "label": "race: 5 · center: 2",
        "n": 445,
        "missing": 0,
        "n_levels": 5,
        "mode_level": "Disagree",
        "freq": [
          {
            "level": "Disagree",
            "count": 239,
            "pct": 53.7
          },
          {
            "level": "Neutral",
            "count": 87,
            "pct": 19.6
          },
          {
            "level": "Strongly disagree",
            "count": 83,
            "pct": 18.7
          },
          {
            "level": "Agree",
            "count": 34,
            "pct": 7.6
          },
          {
            "level": "Strongly agree",
            "count": 2,
            "pct": 0.4
          }
        ]
      },
      {
        "label": "race: 5 · center: 3",
        "n": 638,
        "missing": 1,
        "n_levels": 6,
        "mode_level": "Disagree",
        "freq": [
          {
            "level": "Disagree",
            "count": 387,
            "pct": 60.7
          },
          {
            "level": "Neutral",
            "count": 107,
            "pct": 16.8
          },
          {
            "level": "Strongly disagree",
            "count": 94,
            "pct": 14.7
          },
          {
            "level": "Agree",
            "count": 41,
            "pct": 6.4
          },
          {
            "level": "Strongly agree",
            "count": 8,
            "pct": 1.3
          },
          {
            "level": "(Missing)",
            "count": 1,
            "pct": 0.2
          }
        ]
      },
      {
        "label": "race: 5 · center: 4",
        "n": 478,
        "missing": 3,
        "n_levels": 6,
        "mode_level": "Disagree",
        "freq": [
          {
            "level": "Disagree",
            "count": 275,
            "pct": 57.5
          },
          {
            "level": "Neutral",
            "count": 100,
            "pct": 20.9
          },
          {
            "level": "Strongly disagree",
            "count": 71,
            "pct": 14.9
          },
          {
            "level": "Agree",
            "count": 27,
            "pct": 5.6
          },
          {
            "level": "(Missing)",
            "count": 3,
            "pct": 0.6
          },
          {
            "level": "Strongly agree",
            "count": 2,
            "pct": 0.4
          }
        ]
      }
    ],
    "race_sex_center": [
      {
        "label": "race: 4 · sex: 1 · center: 1",
        "n": 210,
        "missing": 2,
        "n_levels": 6,
        "mode_level": "Disagree",
        "freq": [
          {
            "level": "Disagree",
            "count": 78,
            "pct": 37.1
          },
          {
            "level": "Neutral",
            "count": 58,
            "pct": 27.6
          },
          {
            "level": "Agree",
            "count": 42,
            "pct": 20
          },
          {
            "level": "Strongly disagree",
            "count": 26,
            "pct": 12.4
          },
          {
            "level": "Strongly agree",
            "count": 4,
            "pct": 1.9
          },
          {
            "level": "(Missing)",
            "count": 2,
            "pct": 1
          }
        ]
      },
      {
        "label": "race: 4 · sex: 1 · center: 2",
        "n": 146,
        "missing": 0,
        "n_levels": 5,
        "mode_level": "Disagree",
        "freq": [
          {
            "level": "Disagree",
            "count": 64,
            "pct": 43.8
          },
          {
            "level": "Neutral",
            "count": 42,
            "pct": 28.8
          },
          {
            "level": "Strongly disagree",
            "count": 22,
            "pct": 15.1
          },
          {
            "level": "Agree",
            "count": 16,
            "pct": 11
          },
          {
            "level": "Strongly agree",
            "count": 2,
            "pct": 1.4
          }
        ]
      },
      {
        "label": "race: 4 · sex: 1 · center: 3",
        "n": 164,
        "missing": 0,
        "n_levels": 5,
        "mode_level": "Disagree",
        "freq": [
          {
            "level": "Disagree",
            "count": 73,
            "pct": 44.5
          },
          {
            "level": "Neutral",
            "count": 44,
            "pct": 26.8
          },
          {
            "level": "Agree",
            "count": 30,
            "pct": 18.3
          },
          {
            "level": "Strongly disagree",
            "count": 12,
            "pct": 7.3
          },
          {
            "level": "Strongly agree",
            "count": 5,
            "pct": 3
          }
        ]
      },
      {
        "label": "race: 4 · sex: 1 · center: 4",
        "n": 189,
        "missing": 0,
        "n_levels": 5,
        "mode_level": "Disagree",
        "freq": [
          {
            "level": "Disagree",
            "count": 94,
            "pct": 49.7
          },
          {
            "level": "Neutral",
            "count": 57,
            "pct": 30.2
          },
          {
            "level": "Agree",
            "count": 17,
            "pct": 9
          },
          {
            "level": "Strongly disagree",
            "count": 17,
            "pct": 9
          },
          {
            "level": "Strongly agree",
            "count": 4,
            "pct": 2.1
          }
        ]
      },
      {
        "label": "race: 4 · sex: 2 · center: 1",
        "n": 268,
        "missing": 1,
        "n_levels": 6,
        "mode_level": "Disagree",
        "freq": [
          {
            "level": "Disagree",
            "count": 123,
            "pct": 45.9
          },
          {
            "level": "Neutral",
            "count": 51,
            "pct": 19
          },
          {
            "level": "Agree",
            "count": 49,
            "pct": 18.3
          },
          {
            "level": "Strongly disagree",
            "count": 39,
            "pct": 14.6
          },
          {
            "level": "Strongly agree",
            "count": 5,
            "pct": 1.9
          },
          {
            "level": "(Missing)",
            "count": 1,
            "pct": 0.4
          }
        ]
      },
      {
        "label": "race: 4 · sex: 2 · center: 2",
        "n": 224,
        "missing": 0,
        "n_levels": 5,
        "mode_level": "Disagree",
        "freq": [
          {
            "level": "Disagree",
            "count": 92,
            "pct": 41.1
          },
          {
            "level": "Neutral",
            "count": 55,
            "pct": 24.6
          },
          {
            "level": "Agree",
            "count": 38,
            "pct": 17
          },
          {
            "level": "Strongly disagree",
            "count": 36,
            "pct": 16.1
          },
          {
            "level": "Strongly agree",
            "count": 3,
            "pct": 1.3
          }
        ]
      },
      {
        "label": "race: 4 · sex: 2 · center: 3",
        "n": 191,
        "missing": 2,
        "n_levels": 6,
        "mode_level": "Disagree",
        "freq": [
          {
            "level": "Disagree",
            "count": 84,
            "pct": 44
          },
          {
            "level": "Neutral",
            "count": 45,
            "pct": 23.6
          },
          {
            "level": "Strongly disagree",
            "count": 29,
            "pct": 15.2
          },
          {
            "level": "Agree",
            "count": 27,
            "pct": 14.1
          },
          {
            "level": "Strongly agree",
            "count": 4,
            "pct": 2.1
          },
          {
            "level": "(Missing)",
            "count": 2,
            "pct": 1
          }
        ]
      },
      {
        "label": "race: 4 · sex: 2 · center: 4",
        "n": 338,
        "missing": 2,
        "n_levels": 6,
        "mode_level": "Disagree",
        "freq": [
          {
            "level": "Disagree",
            "count": 168,
            "pct": 49.7
          },
          {
            "level": "Neutral",
            "count": 77,
            "pct": 22.8
          },
          {
            "level": "Strongly disagree",
            "count": 48,
            "pct": 14.2
          },
          {
            "level": "Agree",
            "count": 39,
            "pct": 11.5
          },
          {
            "level": "Strongly agree",
            "count": 4,
            "pct": 1.2
          },
          {
            "level": "(Missing)",
            "count": 2,
            "pct": 0.6
          }
        ]
      },
      {
        "label": "race: 5 · sex: 1 · center: 1",
        "n": 200,
        "missing": 3,
        "n_levels": 5,
        "mode_level": "Disagree",
        "freq": [
          {
            "level": "Disagree",
            "count": 117,
            "pct": 58.5
          },
          {
            "level": "Neutral",
            "count": 38,
            "pct": 19
          },
          {
            "level": "Agree",
            "count": 21,
            "pct": 10.5
          },
          {
            "level": "Strongly disagree",
            "count": 21,
            "pct": 10.5
          },
          {
            "level": "(Missing)",
            "count": 3,
            "pct": 1.5
          }
        ]
      },
      {
        "label": "race: 5 · sex: 1 · center: 2",
        "n": 220,
        "missing": 0,
        "n_levels": 5,
        "mode_level": "Disagree",
        "freq": [
          {
            "level": "Disagree",
            "count": 117,
            "pct": 53.2
          },
          {
            "level": "Strongly disagree",
            "count": 46,
            "pct": 20.9
          },
          {
            "level": "Neutral",
            "count": 42,
            "pct": 19.1
          },
          {
            "level": "Agree",
            "count": 13,
            "pct": 5.9
          },
          {
            "level": "Strongly agree",
            "count": 2,
            "pct": 0.9
          }
        ]
      },
      {
        "label": "race: 5 · sex: 1 · center: 3",
        "n": 304,
        "missing": 1,
        "n_levels": 6,
        "mode_level": "Disagree",
        "freq": [
          {
            "level": "Disagree",
            "count": 184,
            "pct": 60.5
          },
          {
            "level": "Neutral",
            "count": 58,
            "pct": 19.1
          },
          {
            "level": "Strongly disagree",
            "count": 34,
            "pct": 11.2
          },
          {
            "level": "Agree",
            "count": 24,
            "pct": 7.9
          },
          {
            "level": "Strongly agree",
            "count": 3,
            "pct": 1
          },
          {
            "level": "(Missing)",
            "count": 1,
            "pct": 0.3
          }
        ]
      },
      {
        "label": "race: 5 · sex: 1 · center: 4",
        "n": 186,
        "missing": 1,
        "n_levels": 6,
        "mode_level": "Disagree",
        "freq": [
          {
            "level": "Disagree",
            "count": 116,
            "pct": 62.4
          },
          {
            "level": "Neutral",
            "count": 36,
            "pct": 19.4
          },
          {
            "level": "Strongly disagree",
            "count": 22,
            "pct": 11.8
          },
          {
            "level": "Agree",
            "count": 10,
            "pct": 5.4
          },
          {
            "level": "(Missing)",
            "count": 1,
            "pct": 0.5
          },
          {
            "level": "Strongly agree",
            "count": 1,
            "pct": 0.5
          }
        ]
      },
      {
        "label": "race: 5 · sex: 2 · center: 1",
        "n": 180,
        "missing": 1,
        "n_levels": 6,
        "mode_level": "Disagree",
        "freq": [
          {
            "level": "Disagree",
            "count": 112,
            "pct": 62.2
          },
          {
            "level": "Neutral",
            "count": 35,
            "pct": 19.4
          },
          {
            "level": "Strongly disagree",
            "count": 23,
            "pct": 12.8
          },
          {
            "level": "Agree",
            "count": 7,
            "pct": 3.9
          },
          {
            "level": "Strongly agree",
            "count": 2,
            "pct": 1.1
          },
          {
            "level": "(Missing)",
            "count": 1,
            "pct": 0.6
          }
        ]
      },
      {
        "label": "race: 5 · sex: 2 · center: 2",
        "n": 225,
        "missing": 0,
        "n_levels": 4,
        "mode_level": "Disagree",
        "freq": [
          {
            "level": "Disagree",
            "count": 122,
            "pct": 54.2
          },
          {
            "level": "Neutral",
            "count": 45,
            "pct": 20
          },
          {
            "level": "Strongly disagree",
            "count": 37,
            "pct": 16.4
          },
          {
            "level": "Agree",
            "count": 21,
            "pct": 9.3
          }
        ]
      },
      {
        "label": "race: 5 · sex: 2 · center: 3",
        "n": 334,
        "missing": 0,
        "n_levels": 5,
        "mode_level": "Disagree",
        "freq": [
          {
            "level": "Disagree",
            "count": 203,
            "pct": 60.8
          },
          {
            "level": "Strongly disagree",
            "count": 60,
            "pct": 18
          },
          {
            "level": "Neutral",
            "count": 49,
            "pct": 14.7
          },
          {
            "level": "Agree",
            "count": 17,
            "pct": 5.1
          },
          {
            "level": "Strongly agree",
            "count": 5,
            "pct": 1.5
          }
        ]
      },
      {
        "label": "race: 5 · sex: 2 · center: 4",
        "n": 292,
        "missing": 2,
        "n_levels": 6,
        "mode_level": "Disagree",
        "freq": [
          {
            "level": "Disagree",
            "count": 159,
            "pct": 54.5
          },
          {
            "level": "Neutral",
            "count": 64,
            "pct": 21.9
          },
          {
            "level": "Strongly disagree",
            "count": 49,
            "pct": 16.8
          },
          {
            "level": "Agree",
            "count": 17,
            "pct": 5.8
          },
          {
            "level": "(Missing)",
            "count": 2,
            "pct": 0.7
          },
          {
            "level": "Strongly agree",
            "count": 1,
            "pct": 0.3
          }
        ]
      }
    ]
  }
}
